Workbook

Sheet Flujo General
A1: ANALISIS DE RIESGO CREDITICIO
A3: Recolección de Datos | C3: Construcción del Scoring crediticio | G3: Evaluación y Aprobación Automática
A5: Datos Internos (sistema) | C5: Cálculo del puntaje | G5: Monitoreo del comportamiento / Otras Opciones
A7: Datos Externos (Verificación)
D10: ¿Aprobado? | E10: No | G10: Préstamo Rechazado
A11: Estructura
A13: Tecnología / Desarrollo | D13: SI
C15: Inicia flujo de Otorgamiento

Sheet Flujo detalle Otorgamiento
A1: Flujo Operativo
A2: Otorgamiento de Línea de Crédito a 45 Días
A6: CLIENTE
A12: SOFWARE

Sheet Resultado Otorgamiento 
A1: Resultado de otorgamiento
B4: Etiqueta | C4: Valor | D4: Origen
B5: Decisión de Crédito
B6: Solicitante: | C6: ='Solicitud de Crédito'!D6 -> Empresa Ejemplo S.A. | D6: =D6,Solicitud de Crédito
B7: Monto Solicitado: | C7: 50000 | D7: Pantalla de reistro de cred solicitado
B8: Score de Otorgamiento : | C8: ='Scoring de Otorgamiento'!D12 -> 1480 | D8: =D12, Scoring de Otorgamiento
B9: Decisión de Crédito | C9: ='Scoring de Otorgamiento'!D13 -> Aprobado | D9: =D13,Scoring de Otorgamiento

Sheet Solicitud de Crédito
A1: SOLICITUD DE CRÉDITO
B4: Etiqueta | C4: Tipo de Dato | D4: Ejemplo | E4: Calificación Interna
B5: Información del Solicitante
B6: Razón Social: | C6: Texto | D6: Empresa Ejemplo S.A. | E6: =IF(D6="",0,100) -> 100
B7: RFC: | C7: Texto | D7: ABC123456XYZ | E7: =IF(D7="",0,100) -> 100
B8: Representante Legal: | C8: Texto | D8: Juan Pérez | E8: =IF(D8="",0,100) -> 100
B9: Contacto: | C9: Texto | D9: 55 1234 5678 | E9: =IF(D9="",0,100) -> 100
B10: Giro del Negocio | C10: Texto | D10: Construcción | E10: =VLOOKUP(D10,Despegables!$D$4:$E$9,2,0) -> 100
B11: Antigüedad del Negocio (años): | C11: Número | D11: 3 | E11: =IF(D11>=2,100,0) -> 100
B12: Ubicación: | C12: Texto | D12: Zona comercial | E12: =VLOOKUP(D12,Despegables!$I$4:$J$6,2,0) -> 90
E13: =SUM(E6:E12) -> 690
B15: Fuentes de Información
B16: Identificación Oficial Representante Legal | C16: Despegable | D16: Si | E16: =IF(D16="Si",100,0) -> 100
B17: Comprobante de Domicilio de la empresa | C17: Despegable | D17: Si | E17: =IF(D17="Si",100,0) -> 100
B18: Acta Constitutiva | C18: Despegable | D18: No | E18: =IF(D18="Si",100,0) -> 0
B19: Reporte de Buro de Crédito | C19: Despegable | D19: Si | E19: =IF(D19="Si",100,0) -> 100
B20: Estados de Cuenta Bancario | C20: Despegable | D20: No | E20: =IF(D20="Si",100,0) -> 0
B21: Constancia de Situación Fiscal | C21: Despegable | D21: Si | E21: =IF(D21="Si",100,0) -> 100
E22: =SUM(E16:E21) -> 400

Sheet Análisis Financiero 
A1: ANALISIS FINANCIERO
B4: Etiqueta | C4: Valor (Ejemplo) | D4: Fórmula / Descripción | E4: % | F4: Calificación Interna
B5: Estado de Resultados (último mes)
B6: Ventas Netas ($): | C6: 200000
B7: Costo de Ventas ($): | C7: 120000
B8: Utilidad Bruta ($): | C8: =C6-C7 -> 80000 | D8: =B6 - B7 | E8: =C8/C6 -> 0.4 | F8: =VLOOKUP(E8,Despegables!$C$13:$F$18,4,1) -> 80
B9: Gastos de Operación ($): | C9: 50000
B10: Utilidad de Operación ($): | C10: =C8-C9 -> 30000 | D10: =B8-B9 | E10: =C10/C6 -> 0.15 | F10: =VLOOKUP(E10,Despegables!$C$19:$F$24,4,1) -> 50
F11: =SUM(F8+F10) -> 130
B13: Balance General
B14: Cuentas por Cobrar ($): | C14: 60000
B15: Inventario ($): | C15: 30000
B16: Pasivos a Corto Plazo ($): | C16: 50000
B18: Indicadores Financieros
B19: Razón de Liquidez (Capital de Trabajo): | C19: =((C14+C15)/C16)/100 -> 0.018 | D19: =(B14+B15)/B16 | F19: =VLOOKUP(C19,Despegables!$J$13:$M$15,4,1) -> 100
B20: Margen de Utilidad Operativa: | C20: =(C10/C6) -> 0.15 | D20: =B10/B6 | F20: =VLOOKUP(C20,Despegables!$J$19:$M$22,4,1) -> 70
F21: =SUM(F19:F20) -> 170

Sheet Historial Crediticio
A1: Historial Crediticio
A4: Buro de crédito del año en curso
B6: Variable | C6: Calificación | D6: Puntuación
B7: Score Buró de Crédito | C7: 700 | D7: =VLOOKUP(C7,Despegables!$J$26:$M$28,4,1) -> 90

Sheet Scoring de Otorgamiento
A1: Scoring de Otorgamiento
B5: Criterio | C5: Ponderación | D5: Puntaje Parcial
B6: Modelo de Scoring Rápido
B7: 1. Información del solicitante | C7: 700 | D7: ='Solicitud de Crédito'!E13 -> 690
B8: 2. Fuentes de Información | C8: 600 | D8: ='Solicitud de Crédito'!E22 -> 400
B9: 3. Estado de Resultados | C9: 200 | D9: ='Análisis Financiero '!F11 -> 130
B10: 4. Indicadores Financieros | C10: 200 | D10: ='Análisis Financiero '!F21 -> 170
B11: 4. Historial Crediticio (Buró) | C11: 100 | D11: ='Historial Crediticio'!D7 -> 90
B12: Puntuación Total: | C12: =SUM(C7:C11) -> 1800 | D12: =SUM(D7:D11) -> 1480
B13: Recomendación: | C13: =D12/C12 -> 0.82222222 | D13: =VLOOKUP(C13,Despegables!$M$4:$P$5,4,1) -> Aprobado
G14: Colores
B15: META SCORING | C15: % AVANCE | D15: Ancho Linea | E15: Vacio | G15: Rojo | H15: Naranja | I15: Amarillo | J15: Verde | K15: Total
B16: =C12 -> 1800 | C16: =(D12/B16)*100 -> 82.222222 | D16: 3 | E16: =SUM(G16:K16)-C16-D16 -> 114.77778 | G16: 25 | H16: 25 | I16: 25 | J16: 25 | K16: =SUM(G16:J16) -> 100

Sheet PE
A1: RESULTADOS TOTAL DE SEGUIMIENTO
A3: Indicador | B3: Valor
A4: Exposición Total (EAD) | B4: =SUM(G21:G29) -> 15150000
A5: Pérdida Esperada Total | B5: =SUM(H21:H29) -> 410840
A6: % de Pérdida Esperada | B6: =B5/B4 -> 0.027118152
A8: FORMULA
A9: PE | B9: Pérdida Esperada
A10: PD | B10: Probabilidad de Incumplimiento
A11: EAD | B11: Exposición en el incumplimiento
A12: LGD | B12: Severidad de Pérdida
A14: PE= PD * EAD * LGD
A16: DESARROLLO DE LA BASE DE DATOS DE CLIENTES
A18: Es importante incluir todas las variables de cálculo
A20: Cliente | B20: Límite de Crédito | C20: Saldo Utilizado | D20: Días en Mora | E20: PD (Individual ) (%) | F20: LGD (Asumida) (%) | G20: EAD (Individual ) | H20: Pérdida Esperada (PE = PD*EAD*LGD)
A21: Cliente A | B21: 100000 | C21: 80000 | D21: 0 | E21: =VLOOKUP(D21,'[1]PD x Días Mora'!$A$4:$D$11,4,1) -> 0.02 | F21: 0.4 | G21: =C21 -> 80000 | H21: =E21*G21*F21 -> 640
A22: Cliente B | B22: 4000000 | C22: 3500000 | D22: 10 | E22: =VLOOKUP(D22,'[1]PD x Días Mora'!$A$4:$D$11,4,1) -> 0.03 | F22: 0.4 | G22: =C22 -> 3500000 | H22: =E22*G22*F22 -> 42000
A23: Cliente C | B23: 150000 | C23: 120000 | D23: 25 | E23: =VLOOKUP(D23,'[1]PD x Días Mora'!$A$4:$D$11,4,1) -> 0.1 | F23: 0.4 | G23: =C23 -> 120000 | H23: =E23*G23*F23 -> 4800
A24: Cliente D | B24: 500000 | C24: 350000 | D24: 15 | E24: =VLOOKUP(D24,'[1]PD x Días Mora'!$A$4:$D$11,4,1) -> 0.05 | F24: 0.4 | G24: =C24 -> 350000 | H24: =E24*G24*F24 -> 7000
A25: Cliente E | B25: 700000 | C25: 500000 | D25: 20 | E25: =VLOOKUP(D25,'[1]PD x Días Mora'!$A$4:$D$11,4,1) -> 0.07 | F25: 0.4 | G25: =C25 -> 500000 | H25: =E25*G25*F25 -> 14000
A26: Cliente F | B26: 1000000 | C26: 800000 | D26: 5 | E26: =VLOOKUP(D26,'[1]PD x Días Mora'!$A$4:$D$11,4,1) -> 0.02 | F26: 0.4 | G26: =C26 -> 800000 | H26: =E26*G26*F26 -> 6400
A27: Cliente G | B27: 3000000 | C27: 2000000 | D27: 30 | E27: =VLOOKUP(D27,'[1]PD x Días Mora'!$A$4:$D$11,4,1) -> 0.1 | F27: 0.4 | G27: =C27 -> 2000000 | H27: =E27*G27*F27 -> 80000
A28: Cliente H | B28: 5000000 | C28: 2800000 | D28: 12 | E28: =VLOOKUP(D28,'[1]PD x Días Mora'!$A$4:$D$11,4,1) -> 0.05 | F28: 0.4 | G28: =C28 -> 2800000 | H28: =E28*G28*F28 -> 56000
A29: Cliente I | B29: 5000000 | C29: 5000000 | D29: 28 | E29: =VLOOKUP(D29,'[1]PD x Días Mora'!$A$4:$D$11,4,1) -> 0.1 | F29: 0.4 | G29: =C29 -> 5000000 | H29: =E29*G29*F29 -> 200000

Sheet PLD Sofware
A1: Requisición de Cumplimientos PLD (Lo que debe contener el sofware) | F1: Documentación necesaria para Soportar la Autorización
A2: Disposiciones de Carácter Genenral en Materia de PLD / FT (DCG) emitidas por la CNBV | F2: Evidencia Técnica y Documental para validar su cumplimiento
A4: Numeral CNBV | B4: Modulo | C4: Obligacion PLD | D4: Detalle | F4: Consecutivo | G4: Documento | H4: Detalle
A5: 2. Requerimientos Funcionales (lo que hace el sistema) | B5: A | C5: Módulo de Identificación y conocimiento del cliente (KYC) | D5: Captura Estructurada de Información de Clientes (personas físicas y morales) | F5: 1 | G5: Manual de PLD Actualizado | H5: Describa el uso del sistema
A6: 2. Requerimientos Funcionales (lo que hace el sistema) | B6: A | C6: Módulo de Identificación y conocimiento del cliente (KYC) | D6: Digitalización y resguardo de documentos KYC ( INE, Actas, RFC, Comprobantes, etc) | H6: Especifique procesos automatizados, validaciones y flujos
A7: 2. Requerimientos Funcionales (lo que hace el sistema) | B7: A | C7: Módulo de Identificación y conocimiento del cliente (KYC) | D7: Validación automática de campos obligatorios | H7: Identifique responsables y periodicidades
A8: 2. Requerimientos Funcionales (lo que hace el sistema) | B8: A | C8: Módulo de Identificación y conocimiento del cliente (KYC) | D8: Clasificación Inicial del Cliente (Según tipo, actividad y zona geográfica) | F8: 2 | G8: Manual Técnico o Documento de Arquitectura del sistema | H8: Infraestructura tecnológica (servidores, nube, seguridad, backups)
A9: 2. Requerimientos Funcionales (lo que hace el sistema) | B9: A | C9: Módulo de Identificación y conocimiento del cliente (KYC) | D9: Asignación automática de nivel de riesgo (bajo, medio, alto) mediante una matriz configurable. | H9: Integraciones con otros sistemas (core financiero o CRM)
A10: 2. Requerimientos Funcionales (lo que hace el sistema) | B10: B | C10: Módulo de listas oficiales y PEPs | D10: Conexión o actualización automática con listas de Personas Bloqueadas (UIF) | H10: Protocolos de seguridad (encriptación , control de accesos, logs)
A11: 2. Requerimientos Funcionales (lo que hace el sistema) | B11: B | C11: Módulo de listas oficiales y PEPs | D11: Conexión o actualización automática con listas de Personas Bloqueadas OFAC/ONU/UE/FinCEN/Interpol, etc | F11: 3 | G11: Bitacora de validaciones y pruebas | H11: Evidencia de que el sistema genera alertas, reportes, y realiza screening correctamente
A12: 2. Requerimientos Funcionales (lo que hace el sistema) | B12: B | C12: Módulo de listas oficiales y PEPs | D12: Registro de Fecha y resultado de cada validación | F12: 4 | G12: Informe de Auditoría Interna o Externa PLD | H12: validando que el sistema cumple con los requisitos de la CNBV
A13: 2. Requerimientos Funcionales (lo que hace el sistema) | B13: B | C13: Módulo de listas oficiales y PEPs | D13: Identificación y tratamiento de PEPs nacionales y extranjeras
A14: 2. Requerimientos Funcionales (lo que hace el sistema) | B14: C | C14: Monitoreo de Operaciones y Alertas | D14: Registrar todas las operaciones relevantes (>= USD 10,000 aprox. O su rquivalente en MXN)
A15: 2. Requerimientos Funcionales (lo que hace el sistema) | B15: C | C15: Monitoreo de Operaciones y Alertas | D15: Permitir la configuración de parámetros y umbrales personalizados (por cliente o por segmento)
A16: 2. Requerimientos Funcionales (lo que hace el sistema) | B16: C | C16: Monitoreo de Operaciones y Alertas | D16: Detectar operaciones inusuales o atípicas según patrones de comportamiento
A17: 2. Requerimientos Funcionales (lo que hace el sistema) | B17: C | C17: Monitoreo de Operaciones y Alertas | D17: Emitir alertas automáticas y bitácora de seguimiento para el oficial de cumplimiento
A18: 2. Requerimientos Funcionales (lo que hace el sistema) | B18: C | C18: Monitoreo de Operaciones y Alertas | D18: Generar automáticamente los reportes RELEVANTES INUSUALES e INTERNAS PREOCUPANTES
A19: 2. Requerimientos Funcionales (lo que hace el sistema) | B19: D | C19: Reportes y Envíos a la CNBV/UIF | D19: Capacidad de generar archivos XML y reportes compatibles con los formatos oficiales de CNBV (Sistema de reportes en Línea - SITI CNBV)
A20: 2. Requerimientos Funcionales (lo que hace el sistema) | B20: D | C20: Reportes y Envíos a la CNBV/UIF | D20: Registro Histórico de reportes enviados, fechas u acuses
A21: 2. Requerimientos Funcionales (lo que hace el sistema) | B21: D | C21: Reportes y Envíos a la CNBV/UIF | D21: Validación de consistencia y errores antes del envío
A22: 2. Requerimientos Funcionales (lo que hace el sistema) | B22: E | C22: Auditoría, Control Interno y Evidencia | D22: Bitácora inalterable de todas las acciones (logs, usuarios, fechas, cambios)
A23: 2. Requerimientos Funcionales (lo que hace el sistema) | B23: E | C23: Auditoría, Control Interno y Evidencia | D23: Control de acceso por roles (Administrador, Cumplimiento, Auditoría, Usuario)
A24: 2. Requerimientos Funcionales (lo que hace el sistema) | B24: E | C24: Auditoría, Control Interno y Evidencia | D24: Reporte de Aurditoría automatizado (quien modifico que, cuando y por qu´q)
... A27: 2. Requerimientos Funcionales (lo que hace el sistema) | B27: F | C27: Capacitación y Documentación | D27: Historial de cumplimiento de obligaciones (fechas, responsables, evidencias)

Sheet Despegables
A3: Fuentes de Información | C3: Variable | D3: Sub Variable | E3: Puntuación | H3: Variable | I3: Sub Variable | J3: Puntuación
A4: Si | C4: Giro del negocio | D4: Construcción | E4: 100 | F4: Asignación de puntuación de cuerdo al tipo de negocio al que se otroga el crédito, con criterios de generación de flujos de efectivo. | H4: Zona / Ubicación | I4: Fronteriza | J4: 100 | K4: Asignación de puntuación de acuerdo a la ubicación donde se encuentre el negocio | M4: 0.01 | N4: 0.59 | O4: 1% a 49% | P4: No aprobado
A5: No | D5: Manufactura | E5: 100 | I5: Zona comercial | J5: 90 | M5: 0.6 | N5: 1 | O5: 60% a 100% | P5: Aprobado
D6: Transporte | E6: 100 | I6: Zona industrial | J6: 80
D7: Comercial | E7: 100
D8: Industrial | E8: 100
D9: Servicios | E9: 100
A12: Variable | B12: Sub Variable | C12: De | D12: A | E12: % Resultado | F12: Puntuación | H12: Variable | I12: Sub Variable | J12: De | K12: A | L12: Resultado (%) | M12: Puntuación
A13: Estado de resultados | B13: Utilidad Buta | C13: 0.01 | D13: 0.1 | E13: De 1% a 10% | F13: 0 | H13: Razón de Liquidez | I13: Baja | J13: 0 | K13: 1 | L13: De 0% a 1% | M13: 30 | N13: Puede variar de acuerdo al giro de la empresa
C14: 0.11 | D14: 0.2 | E14: de 11% a 20% | F14: 50 | I14: Media | J14: =110%/100 -> 0.011 | K14: =(150%)/100 -> 0.015 | L14: de 1.1% a 1.5% | M14: 70
C15: 0.21 | D15: 0.3 | E15: de 21% a 30% | F15: 50 | I15: Alta | J15: =(151%)/100 -> 0.0151 | K15: =(250%)/100 -> 0.025 | L15: de 1.5% a 2.5% | M15: 100
C16: 0.31 | D16: 0.4 | E16: de 31% a 40% | F16: 80
C17: 0.41 | D17: 0.5 | E17: de 41% a 50% | F17: 90
C18: 0.51 | E18: De 50% en adelante | F18: 100 | H18: Variable | I18: Sub Variable | J18: De | K18: A | L18: Resultado | M18: Puntuación
B19: Utilidad de Operación | C19: 0.01 | D19: 0.1 | E19: De 1% a 10% | F19: 50 | H19: Margen de utilidad operativa | I19: Baja | J19: 0 | K19: 0.0009 | L19: De 0% a 9% | M19: 30 | N19: Puede variar de acuerdo al giro de la empresa
C20: 0.11 | D20: 0.2 | E20: de 11% a 20% | F20: 50 | I20: Promedio | J20: 0.1 | K20: 0.15 | L20: De 10% a 15% | M20: 70
C21: 0.21 | D21: 0.3 | E21: de 21% a 30% | F21: 70 | I21: Fuerte | J21: 0.16 | K21: 0.2 | L21: de 16% a 20% | M21: 90
C22: 0.31 | D22: 0.4 | E22: de 31% a 40% | F22: 80 | I22: Excelente | J22: 0.21 | L22: de 21% en adelante | M22: 100
C23: 0.41 | D23: 0.5 | E23: de 41% a 50% | F23: 100
C24: 0.51 | E24: De 50% en adelante | F24: 100
H25: Variable | I25: Sub Variable | J25: De | K25: A | L25: Resultado (%) | M25: Puntuación
H26: Score de Buro de Crédito | I26: Baja | J26: 0 | K26: 600 | L26: De 0 a 600 | M26: 40
I27: Media | J27: 601 | K27: 700 | L27: de 601 a 700 | M27: 90
I28: Alta | J28: 701 | L28: de 701 | M28: 100
