Workbook
Name Inicio_del_proyecto: #REF!
Name Inicio_del_proyecto: #REF!
Name Inicio_del_proyecto: #REF!
Name Inicio_del_proyecto: #REF!
Name Semana_para_mostrar: #REF!
Name Semana_para_mostrar: #REF!
Name Semana_para_mostrar: #REF!
Name Semana_para_mostrar: #REF!
Name YO: #REF!
Name YO: #REF!
Name YO: #REF!

Sheet Scoring Interno
A1: REQUISITOS PARA SOLICITUD DEL CREDITO
J2: RIESGO
A3: Variable | B3: Peso Variable (%) | C3: Scorig Inetrno | E3: META SCORING | F3: % AVANCE | G3: LINEA | H3: VACIO | J3: RIESGO ALTO | K3: RIESGO MEDIO ALTO | L3: RIESGO MEDIO BAJO | M3: RIESGO BAJO | N3: TOTAL
A4: Antigüedad del negocio mínima de 2 años | B4: 100 | C4: ='Sub variables gral'!E5 -> 100 | E4: 1300 | F4: =(C17/E4)*100 -> 79.230769 | G4: 3 | H4: =SUM(J4:N4)-F4-G4 -> 117.76923 | J4: 25 | K4: 25 | L4: 25 | M4: 25 | N4: =SUM(J4:M4) -> 100
A5: Giro del negocio | B5: 100 | C5: ='Sub variables catalogo'!C7 -> 100 | J5: Riesgo Alto
A6: Zona / Ubicación | B6: 100 | C6: ='Sub variables catalogo'!I8 -> 100 | J6: Riesgo Medio Alto
A7: Enfoque del crédito (capital de trabajo, Instalaciones y equipamiento) | B7: 100 | C7: ='Sub variables gral'!E9 -> 100 | J7: Riegos Medio
A8: Documentos básicos de identificación (CURP,INE, Comprobante de domicilio de empresa y persona) | B8: 100 | C8: ='Sub variables gral'!E13 -> 100 | J8: Riesgo Bajo
A9: Acta Constitutiva, poderes vigentes, asambleas de cambios en capital y modificaciones en estatutos. (Acta Constitutiva y poderes con inscripción al Regisitro público de la propiedad) | B9: 100 | C9: ='Sub variables gral'!E19 -> 90
A10: Constancia de situación fiscal de la empresa y del principal accionista. | B10: 100 | C10: ='Sub variables gral'!E26 -> 50
A11: Comprobante de domicilio reciente de la empresa (no mayor a 3 meses). | B11: 100 | C11: ='Sub variables gral'!E29 -> 100
A12: Estados Financieros de los últimos tres cierres así como del período en curso (incluyendo analíticas de las principales cuentas de balance). | B12: 100 | C12: ='Sub variables Buro'!E11 -> 90
A13: Declaraciones anuales de los últimos tres períodos (incluyendo acuse). | B13: 100 | C13: ='Sub variables gral'!E32 -> 100
A14: Tabla de pasivos financieros. | B14: 100 | C14: ='Sub variables gral'!E35 -> 0
A15: Relación patrimonial del principal accionista. | B15: 100 | C15: ='Sub variables gral'!E38 -> 100
A16: Copia de acta de matrimonio del principal accionista. | B16: 100 | C16: ='Sub variables gral'!E41 -> 0
A17: SCORING SOLVENCIA | B17: =SUM(B4:B16) -> 1300 | C17: =SUM(C4:C16) -> 1030

Sheet Sub variables gral
A1: Layout General | E1: Puntaje Total
E2: =E43 -> 740
A4: Variable | B4: Condición | C4: Puntaje Asignado | D4: Castiga / Premia | E4: Puntaje total
A5: Antigüedad del negocio mínima de 1 año | B5: Si el negocio tiene antigüedad mayor a 1 año = 100% | C5: 100 | D5: Premia | E5: =C5 -> 100
B6: Si el negocio tiene de 11 a 12 mese de antigüedad = 80% | C6: 80 | D6: Castiga
B7: Si el negocio tiene 10 meses o menos de antigüedad = 70% | C7: 70 | D7: Castiga
A9: Enfoque del crédito | B9: Capital de Trabajo | C9: 100 | D9: Premia | E9: =C9 -> 100
B10: Instalaciones | C10: 100 | D10: Premia
B11: Equipmiento | C11: 100 | D11: Premia
A13: Documentos básicos de identificación del representante legan y principal accionista | B13: CURP | C13: 25 | D13: Premia | E13: =C13+C14+C15+C16 -> 100
B14: INE | C14: 25 | D14: Premia
B15: Comprobante de domicilio de empresa | C15: 25 | D15: Premia
B16: Comprobante de domicilio de la persona | C16: 25 | D16: Premia
B17: Total de documentos presentados | C17: =SUM(C13:C16) -> 100
A19: Acta Constitutiva, poderes vigentes, asambleas de cambios en capital y modificaciones en estatutos. (Acta Constitutiva y poderes con inscripción al Regisitro público de la propiedad) | B19: Acta Constitutiva con inscripción al Regisitro público de la propiedad | C19: 100 | D19: Premia | E19: =C24 -> 90
B20: Poderes vigente con inscripción al Regisitro público de la propiedad | C20: 100 | D20: Premia
B21: Asambleas de cambios en capital | C21: 85 | D21: Castiga
B22: Modificaciones en estatutos | C22: 85 | D22: Castiga
B23: El Acta Constitutiva y los Poderes vigentes no se encuentran inscritos en el Registro Público de la Propiedad | C23: 80 | D23: Castiga
B24: El Acta Constitutiva y los Poderes vigentes no se encuentran inscritos en el Registro Público de la Propiedad + Asamblea de cambios en capital o modificaciones en estatutos | C24: 90 | D24: Castiga
A26: Constancia de situación fiscal | B26: De la Empresa | C26: 50 | D26: Premia | E26: =C26 -> 50
B27: Del principal accionista | C27: 50 | D27: Premia
A29: Comprobante de domicilio reciente de la empresa (no mayor a 3 meses). | B29: Presenta comprobante | C29: 100 | D29: Premia | E29: =C29 -> 100
B30: No presenta comprobante | C30: 0 | D30: Castiga
A32: Declaraciones anuales de los últimos tres períodos (incluyendo acuse). | B32: Si presenta declaraciones anuales | C32: 100 | D32: Premia | E32: =C32 -> 100
B33: No presenta declaraciones anuales | C33: 0 | D33: Castiga
A35: Tabla de pasivos financieros. | B35: Si presenta tabla de pasivos financieros | C35: 100 | D35: Premia | E35: =C36 -> 0
B36: No presenta tabla de pasivos financieros | C36: 0 | D36: Castiga
A38: Relación patrimonial del principal accionista. | B38: Si presenta relación patrimonial del principal accionista | C38: 100 | D38: Premia | E38: =C38 -> 100
B39: No presenta relación patrimonial del principal accionista | C39: 0 | D39: Castiga
A41: Copia de acta de matrimonio del principal accionista. | B41: Si presenta copia de acta de matrimonio del principal accionista | C41: 100 | D41: Premia | E41: =C42 -> 0
B42: No presenta copia de acta de matrimonio del principal accionista | C42: 0 | D42: Castiga
E43: =SUM(E5:E42) -> 740

Sheet Sub variables Buro
A1: SCORING SUB - VARIABLES
C2: SCORE FINAL | D2: =SUM(E11+E19+E28+E35) -> 90
E3: CALIFICACIONES
A5: Estados Financieros | B5: Sub - variable | C5: Peso variable (%) | E5: Estados Financieros
A6: 5. Estados Financieros de los últimos tres cierres así como del período en curso (incluyendo analíticas de las principales cuentas de balance). | B6: Análisis Vertical | C6: 20 | D6: Cada uno de los analisis a a los estados financieros generaran un puntaje de hasta el 20% de acuerdo a los resultados obtenidos y a la importancia que la institución le de a cada uno. | E6: 15
B7: Análisis Horizontal, | C7: 20 | E7: 20
B8: Análisis de Apalancamiento | C8: 20 | E8: 18
B9: Análisis de Liquidez | C9: 20 | E9: 17
B10: Análisis de Rentabilidad | C10: 20 | E10: 20
A11: Score Estados financieros | C11: =SUM(C6:C10) -> 100 | E11: =SUM(E6:E10) -> 90
C12: Hasta 20% de acuerdo a los resultados de cada análisis

Sheet Sub variables catalogo
A1: SCORING EMPRESA
A5: Variable | B5: Sub Variable | C5: Puntuación | G5: Variable | H5: Sub Variable | I5: Puntuación
A6: Giro del negocio | B6: Construcción | C6: 100 | D6: Asignación de puntuación de cuerdo al tipo de negocio al que se otroga el crédito, con criterios de generación de flujos de efectivo. | G6: Zona / Ubicación | H6: Fronteriza | I6: 100 | J6: Asignación de puntuación de acuerdo a la ubicación donde se encuentre el negocio
B7: Manufactura | C7: 100 | H7: Zona comercial | I7: 90
B8: Transporte | C8: 100 | H8: Zona industrial | I8: 100
B9: Comercial | C9: 100
B10: Industrial | C10: 100
B11: Servicios | C11: 100

Sheet MATRIZ DE RIESGO % RESUMEN
C2: MATRIZ DE RIESGOS
D5: RIESGO ALTO | F5: RIESGO MEDIO ALTO | I5: RIESGO MEDIO BAJO | L5: RIESGO BAJO
A6: Créditos Nuevos | B6: Monto Solicitado ($ Pesos) | C6: Plazo (Días) | D6: Menor a 652 | F6: 652 a 680 | I6: 681 a 700 | L6: 701 en adelante
D7: 20% - 24% | E7: 25% - 30% | F7: 31% - 39% | G7: 40% - 49% | H7: 50% - 60% | I7: 61% - 70% | J7: 71% - 80% | K7: 81% - 90% | L7: 411 - 420 | M7: 421 - 430 | N7: > 430
D8: Con Aval + Garantía | F8: Con Aval + Garantía | I8: Con Garantía | L8: No Aplica
B9: de $500,000 a $1´500,000 | C9: 15 | D9: NO ES PROSPECTO DE CRÉDITO | F9: 0.35 | I9: 0.65 | L9: HASTA 100% DE LA LÍNEA DE CRÉDITO
C10: 20
C11: 25 | G11: 0.55 | J11: 0.8
C12: 30 | H12: 0.6 | K12: 0.9
B13: de $1´500,001 a $3'000,000 | C13: 15 | F13: 0.3 | I13: 0.65
C14: 20
C15: 25 | G15: 0.5 | J15: 0.8
C16: 30 | H16: 0.55 | K16: 0.9
B17: de $3'000,001 a $4´500,000 | C17: 15 | F17: 0.25 | I17: 0.65
C18: 20
C19: 25 | G19: 0.45 | J19: 0.8
C20: 30 | H20: 0.5 | K20: 0.9
B21: de $4´500,001 a $6´000,000 | C21: 15 | F21: 0.2 | I21: 0.65
C22: 20
C23: 25 | G23: 0.4 | J23: 0.8
C24: 30
C25: 35 | H25: 0.45 | K25: 0.9
B26: de $6´000,001 a $7'500,000 | C26: 15 | I26: 0.65
C27: 20
C28: 25 | J28: 0.8
C29: 30
C30: 35 | K30: 0.9
C31: 40
B32: de $7'500,001 a $10´000,000 | C32: 15
C33: 20
C34: 25
C35: 30
C36: 35
C37: 40
C38: 45

Sheet MATRIZ DE RIESGO $ RESUMEN
C2: MATRIZ DE RIESGOS
D5: RIESGO ALTO | F5: RIESGO MEDIO ALTO | J5: RIESGO MEDIO BAJO | M5: RIESGO BAJO
A6: Créditos Nuevos | B6: Monto Solicitado ($ Pesos) | C6: Plazo (Días) | D6: Menor a 652 | F6: 652 a 680 | J6: 681 a 700 | M6: 701 en adelante
D7: 20% - 24% | E7: 25% - 30% | F7: 31% - 39% | G7: 40% - 49% | I7: 50% - 60% | J7: 61% - 70% | K7: 71% - 80% | L7: 81% - 90% | M7: 411 - 420 | N7: 421 - 430 | O7: > 430
D8: Con Aval + Garantía | F8: Con Aval + Garantía | J8: Con Garantía | M8: No Aplica
B9: de $500,000 a $1´500,000 | C9: 15 | D9: NO ES PROSPECTO DE CRÉDITO | F9: =1500000*0.35 -> 525000 | J9: =1500000*0.65 -> 975000 | M9: HASTA 100% DE LA LÍNEA DE CRÉDITO
C10: 20
C11: 25 | G11: =1500000*0.55 -> 825000 | K11: =1500000*0.8 -> 1200000
C13: 30 | I13: =1500000*0.6 -> 900000 | L13: =1500000*0.9 -> 1350000
B15: de $1´500,001 a $3'000,000 | C15: 15 | F15: =3000000*0.3 -> 900000 | J15: =3000000*0.65 -> 1950000
C16: 20
C17: 25 | G17: =3000000*0.5 -> 1500000 | K17: =3000000*0.8 -> 2400000
C19: 30 | I19: =3000000*0.55 -> 1650000 | L19: =3000000*0.9 -> 2700000
B21: de $3'000,001 a $4´500,000 | C21: 15 | F21: =4500000*0.25 -> 1125000 | J21: =4500000*0.65 -> 2925000
C22: 20
C23: 25 | G23: =4500000*0.45 -> 2025000 | K23: =4500000*0.8 -> 3600000
C25: 30 | I25: =4500000*0.5 -> 2250000 | L25: =4500000*0.9 -> 4050000
B27: de $4´500,001 a $6´000,000 | C27: 15 | F27: =6000000*0.2 -> 1200000 | J27: =6000000*0.65 -> 3900000
C28: 20
C29: 25 | G29: =6000000*0.4 -> 2400000 | K29: =6000000*0.8 -> 4800000
C30: 30
I31: =6000000*0.45 -> 2700000 | L31: =6000000*0.9 -> 5400000
C32: 35
B33: de $6´000,001 a $7'500,000 | C33: 15 | J33: =7500000*0.65 -> 4875000
C34: 20
C35: 25 | K35: =7500000*0.8 -> 6000000
C36: 30
C37: 35 | L37: =7500000*0.9 -> 6750000
C38: 40
B39: de $7'500,001 a $10´000,000 | C39: 15
C40: 20
C41: 25
C42: 30
C43: 35
C44: 40
C45: 45
I49: 11 | J49: 12 | M49: 13
B55: MONTOS PROPUESTOS PARA EL PRIMER CREDITO, CON POSIBILIDAD DE INCREMENTAR EL MONTO EN LA SIGUIENTE LINEA
